Metadata-Version: 1.1
Name: gotcha
Version: 0.0.1
Summary: A gotcha keywords parser
Home-page: http://github.com/meowstars/gotcha
Author: Yann 'Meow' Bordenave
Author-email: meow@meowstars.org
License: LGPLv3
Platform: UNKNOWN
Classifier: Programming Language :: Python
Classifier: License :: OSI Approved :: GNU Lesser General Public License v3 (LGPLv3)
Classifier: Natural Language :: English
Classifier: Topic :: Software Development
